{
  "title": "ANDaNA: Anonymous Named Data Networking Application",
  "abstract": "Content-centric networking -- also known as information-centric networking (ICN) -- shifts emphasis from hosts and interfaces (as in today's Internet) to data. Named data becomes addressable and routable, while locations that currently store that data become irrelevant to applications.\n  Named Data Networking (NDN) is a large collaborative research effort that exemplifies the content-centric approach to networking. NDN has some innate privacy-friendly features, such as lack of source and destination addresses on packets. However, as discussed in this paper, NDN architecture prompts some privacy concerns mainly stemming from the semantic richness of names. We examine privacy-relevant characteristics of NDN and present an initial attempt to achieve communication privacy. Specifically, we design an NDN add-on tool, called ANDaNA, that borrows a number of features from Tor. As we demonstrate via experiments, it provides comparable anonymity with lower relative overhead.",
  "authors": [
    "Steven DiBenedetto",
    "Paolo Gasti",
    "Gene Tsudik",
    "Ersin Uzun"
  ],
  "pdf_url": "https://arxiv.org/pdf/1112.2205v2",
  "source": "arxiv",
  "faculty": "Ersin Uzun",
  "pdf_local": "/home/lab/codebase/projects/personalProjects/tiger_research_buddy/data_next/pdfs/steven_andana_anonymous_named_data_networking_application.pdf",
  "extracted_text": "arXiv:1112.2205v2  [cs.CR]  10 Jan 2012\nANDaNA: Anonymous Named Data Networking Application\nSteven DiBenedetto\nColorado State University\ndibenede@cs.colostate.edu\nPaolo Gasti\nGene Tsudik\nUniversity of California, Irvine\n{pgasti,gtsudik}@uci.edu\nErsin Uzun\nPalo Alto Research Center\nersin.uzun@parc.com\nAbstract\nContent-centric\nnetworking\n\u2014\nalso\nknown\nas\ninformation-centric networking (ICN) \u2014 shifts empha-\nsis from hosts and interfaces (as in today\u2019s Internet) to\ndata. Named data becomes addressable and routable,\nwhile locations that currently store that data become ir-\nrelevant to applications.\nNamed Data Networking (NDN) is a large collabora-\ntive research effort that exempli\ufb01es the content-centric\napproach to networking. NDN has some innate privacy-\nfriendly features, such as lack of source and destina-\ntion addresses on packets.\nHowever, as discussed in\nthis paper, NDN architecture prompts some privacy con-\ncerns mainly stemming from the semantic richness of\nnames. We examine privacy-relevant characteristics of\nNDN and present an initial attempt to achieve communi-\ncation privacy. Speci\ufb01cally, we design an NDN add-on\ntool, called ANDaNA, that borrows a number of features\nfrom Tor. As we demonstrate via experiments, it provides\ncomparable anonymity with lower relative overhead.\n1\nIntroduction\nAlthough the Internet, as a whole, is a huge global\nsuccess story, it is showing clear signs of age. In the\n1970s, when core ideas underlying today\u2019s Internet were\ndeveloped, telephony was the only example of effec-\ntive global-scale communications. Thus, while the com-\nmunication solution offered by the Internet\u2019s TCP/IP\nsuite was unique and ground-breaking, the communica-\ntion paradigm it focused on was similar to that of tele-\nphony: a point-to-point conversation between two en-\ntities. The communication world has changed dramat-\nically since then and today\u2019s Internet has to accommo-\ndate: information-intensive services, exabytes of con-\ntent created and consumed daily over the Web as well as\na menagerie of mobile devices connected to it. To keep\npace with these changes and move the Internet into the\nfuture, a number of research efforts to design new Inter-\nnet architectures have taken off in the last few years.\nNamed-Data Networking (NDN) [32] is one such ef-\nfort that exempli\ufb01es the content-centric approach [23,\n27, 28] to networking. NDN names content instead of\nlocations (i.e., hosts or interfaces) and thus transforms\ncontent into a \ufb01rst-class entity. NDN also stipulates that\neach piece of content must be signed by its producer.\nThis allows decoupling of trust in content from trust in\nthe entity that might store and/or disseminate that con-\ntent. These NDN features facilitate automatic caching of\ncontent to optimize bandwidth use and enable effective\nsimultaneous utilization of multiple network interfaces.\nHowever, NDN introduces certain challenges that\nmust be addressed in order for it to be a serious can-\ndidate for the future Internet architecture. One major\nargument for a new architecture is the inadequate level\nof security and privacy in today\u2019s Internet. We view\nanonymity as being a critical feature in any new network\narchitecture. It helps people overcome communication\nrestrictions and boundaries as well as evade censorship.\nIn addition, some applications (e.g., e-cash or anony-\nmous publishing) can be successfully deployed only if\nthe underlying network allows users to hide their iden-\ntity [14]. Even if end-users do not care about anonymity\nwith respect to services they access, they might still want\nto hide their activities from employers, governments and\nISPs, since those might censor, misuse or accidentally\nleak sensitive information [19].\nLack of source/destination addresses in NDN helps\nprivacy, since NDN packets carry information only\nabout what is requested but not who is requesting it.\nHowever, a closer look reveals that this is insuf\ufb01cient. In\nparticular, NDN design introduces three important pri-\nvacy challenges:\n1. Name privacy: NDN content names are incen-\ntivized to be semantically related to the content it-\nself. Similar to HTTP headers, names reveal sig-\nni\ufb01cantly more information about content than IP\naddresses. Moreover, an observer can easily de-\ntermine when two requests refer to the same (even\nencrypted) content.\n2. Content privacy:\nNDN allows any entity that\nknows a name to retrieve corresponding content.\nEncryption in NDN is used to enforce access con-\n1\n\n\ntrol and is not applied to publicly available content.\nThus, consumers wanting to retrieve public content\ncannot rely on encryption to hide what they access.\n3. Cache privacy: as with current web proxies, net-\nwork neighbors may learn about each others\u2019 con-\ntent access using timing information to identify\ncache hits.\n4. Signature privacy:\nsince digital signatures in\nNDN content packets are required to be publicly\nveri\ufb01able, identity of a content signer may leak sen-\nsitive information.\nIn this paper, we attempt to address these challenges. We\npresent an initial approach, called ANDaNA that can be\nviewed as an adaptation of onion routing to NDN. Our\napproach is in-line with NDN principles. It is designed\nto take advantage of NDN strengths and work around\nits weaknesses. We optimized ANDaNA for small- to\nmedium-size interactive communication \u2013 such as web-\nbrowsing and instant messaging \u2013 that are characterized\nby moderate amounts of low-latency traf\ufb01c [11].\nWe provide a security analysis of the proposed ap-\nproach under a realistic adversarial model.\nSpecif-\nically, we de\ufb01ne anonymity and unlinkability under\nthis security model and show that these properties hold\nfor ANDaNA. Moreover, ANDaNA is secure with fewer\nanonymizing router hops than Tor.\nWe prototyped\nANDaNA and assessed its performance via experiments\nover a network testbed. Results show that ANDaNA in-\ntroduces less overhead than Tor, especially, for antici-\npated traf\ufb01c patterns.\nWe believe that this work is both timely and impor-\ntant. The former \u2013 because of the recent surge of in-\nterest in content-centric networking and NDN being a\ngood example of this paradigm. (Also, while NDN is\nsuf\ufb01ciently mature to have a functional prototype suit-\nable for experimental use, it is still at an early enough\nstage to be open to change.) The latter \u2013 because it rep-\nresents the \ufb01rst attempt to identify and address privacy\nproblems in a viable candidate for the future Internet ar-\nchitecture.\nBefore discussing details of our approach, we present\nfurther motivation for this work.\nWhy NDN? There are multiple efforts to develop new\ncontent-centric architectures and NDN is only one of\nthose. We focus on NDN because it stands out in sev-\neral aspects. First, it combines some revolutionary ideas\nabout content-based routing that have attracted consider-\nable attention from the networking research community.\nSecond, it builds upon an open-source code-base called\nCCNx [12], that is led and continuously maintained by\nan industrial research lab (PARC). At the time of this\nwriting (summer 2011), NDN is one of the very few\ncontent-centric architectural proposals with a reasonably\nmature prototype available to the research community.1\nThird, NDN is one of only four projects selected by NSF\nFuture Internet Architectures (FIA) program [20].\nOn the other hand, NDN is an on-going research\nproject and is thus subject to continuous change. How-\never, we believe that it represents a good example of\ncontent-centric networking design and at least some of\nits concepts will in\ufb02uence the future of networking.\nMore importantly, ideas, techniques and analysis dis-\ncussed in this paper are not speci\ufb01c, or limited to, NDN;\nthey are applicable to a wide range of designs, including\nhost-, location- and content-addressable networks.\nApproach.\nNDN follows the proven design principle\nof IP and claims to be the \u201cthin waist\u201d of the communi-\ncations protocol stack. Thus, pushing security or privacy\nservices (that are not critical for all types of communica-\ntion) into this thin waist would contradict its design prin-\nciple. Consequently, as in the case of IP, we believe that\nprivacy tools should run on top of NDN. Looking at pri-\nvacy and anonymity techniques in today\u2019s Internet, one\nwell-established approach is an overlay anonymization\nnetwork, exempli\ufb01ed by Tor [18]. Tor and its relatives\nemploy layers of concentric encryption and intermedi-\nate nodes responsible for peeling off layers as packets\ntravel through the overlay. This is commonly referred\nto as onion routing. Our approach falls into roughly the\nsame category. However, as we discover and discuss in\nthis paper, the task of adapting an anonymization over-\nlay approach to NDN is not as simple as it might initially\nseem.\nScope.\nThe primary focus of this paper is privacy.\nSecurity and other features of NDN are taken as given\nwithout justifying their existence. A number of impor-\ntant NDN-related security topics are out of scope of this\npaper, including: trust management, certi\ufb01cation and re-\nvocation of credentials as well as routing security.\nOrganization.\nWe start with NDN overview and pri-\nvacy analysis in Section 2. Section 3 summarizes related\nwork, followed by the description of ANDaNA in Sec-\ntion 4. Section 5 introduces a formal model for provable\nanonymity and security analysis of ANDaNA. Implemen-\ntation details and performance evaluation results are dis-\ncussed in Section 6. The paper concludes in Section 7.\n2\nNDN Overview\nNDN [32] is a communication architecture based\non named content.2\nRather than addressing content\nby its location, NDN refers to it by name.\nContent\nname is composed of one or more variable-length com-\nponents that are opaque to the network.\nComponent\n1We are aware of only two other content-centric architecture pro-\nposals \u2013 [33] and [36] \u2013 that have public prototypes.\n2Note that we use the terms \u201dcontent\u201d and \u201ddata\u201d interchangeably\nthroughout this paper.\n2\n\n\nboundaries are explicitly delimited by \u201c/\u201d.\nFor ex-\nample, the name of a CNN news content might be:\n/ndn/cnn/news/2011aug20.\nLarge pieces of con-\ntent can be split into fragments with predictable names:\nfragment 137 of a YouTube video could be named:\n/ndn/youtube/videos/video-749.avi/137.\nSince the main abstraction is content, there is no ex-\nplicit notion of \u201chosts\u201d in NDN. (However, their exis-\ntence is assumed.) Communication adheres to the pull\nmodel: content is delivered to consumers only upon ex-\nplicit request. A consumer requests content by sending\nan interest packet. If an entity (a router or a host) can\n\u201csatisfy\u201d a given interest, it returns the corresponding\ncontent packet. Interest and content are the only types\nof packets in NDN. A content packet with name X in\nNDN is never forwarded or routed unless it is preceded\nby an interest for name X.3\nWhen a router receives an interest for name X and\nthere are no pending interests for the same name in its\nPIT (Pending Interests Table), it forwards this interest to\nthe next hop according to its routing table. For each for-\nwarded interest, a router stores some state information,\nincluding the name in the interest and the interface on\nwhich it was received. However, if an interest for X ar-\nrives while there is an entry for the same name in the PIT,\nthe router collapses the present interest (and any subse-\nquent ones for X) storing only the interface on which it\nwas received. When content is returned, the router for-\nwards it out on all interfaces where an interest for X has\nbeen received and \ufb02ushes the corresponding PIT entry.\nNote that, since no additional information is needed to\ndeliver content, an interest does not carry a source ad-\ndress. More detailed discussion of NDN routing can be\nfound in [27].\nIn NDN, each network entity can provide content\ncaching, which is limited only by resource availabil-\nity. For popular content, this allows interests to be sat-\nis\ufb01ed from cached copies distributed over the network,\nthus maximizing resource utilization. NDN deals with\ncontent authenticity and integrity by making digital sig-\nnatures mandatory on all content packets. A signature\nbinds content with its name, and provides origin au-\nthentication no matter how or from where it is retrieved.\nNDN calls entities that publish new content producers.\nWhereas, as follows from the above discussion, entities\nthat request content are called consumers. (Consumers\nand producers are clearly overlapping sets.) Although\ncontent signature veri\ufb01cation is optional in NDN, a sig-\nnature must be veri\ufb01able by any NDN entity. To make\nthis possible, content packets carry additional metadata,\n3Strictly speaking, content named X\u2032 \u0338=\nX can be delivered in\nresponse to an interest for X but only if X is a pre\ufb01x of X\u2032. As an\nexample, the full name of each content packet contains the hash of that\ncontent; however, this hash value is usually not known to consumers\nand is typically omitted from interests.\nsuch as the ID of the content publisher and information\non locating the public key needed for veri\ufb01cation. Pub-\nlic keys are treated as regular content: since all content\nis signed, each public key content is effectively a \u201ccer-\nti\ufb01cate\u201d. NDN does not mandate any particular certi\ufb01-\ncation infrastructure, relegating trust management to in-\ndividual applications.\nPrivate or restricted content in NDN is protected via\nencryption by the content publisher. Once content is dis-\ntributed unencrypted, there is no mechanism to apply\nsubsequent encryption. Speci\ufb01c applications may pro-\nvide a means to explicitly request encryption of content\nby publishers. However, NDN does not currently allow\nconsumers to selectively conceal content corresponding\nto their interests.\nFrom the privacy perspective, lack of source and des-\ntination addresses in NDN packets is a clear advantage\nover IP. In practice, this means that the adversary that\neavesdrops on a link close to a content producer can not\nimmediately identify the consumer(s) who expressed in-\nterest in that content. Moreover, two features of standard\nNDN routers: (1) content caching and (2) collapsing of\nredundant interests, reduce the utility of eavesdropping\nnear a content producer since not all interests for the\nsame content reach its producer.\nOn the other hand, NDN provides no protection\nagainst an adversary that monitors local activity of a spe-\nci\ufb01c consumer. As most content names are expected to\nbe semantically relevant to content itself, interests can\nleak a lot of information about the content they aim to\nretrieve. To mitigate this issue, NDN allows the use\nof \u201cencrypted names\u201d, whereby a producer encrypts the\ntail-end (a few components) of a name [27]. 4 However,\nthis simple approach does not provide much privacy: the\nadversary can link multiple interests for the same con-\ntent \u2013 or those sharing the same name pre\ufb01x \u2013 issued by\ndifferent consumers. Moreover, an adversary can always\nreplay an interest to see what (possibly cached) content\nit returns, even if a name of content is not semantically\nrelevant.\n3\nRelated Work\nThe goal of anonymizing tools and techniques is to\ndecouple actions from entities that perform them. The\nmost basic approach to anonymity is to use a trusted\nanonymizing proxy. A proxy is typically interposed be-\ntween a sender and a receiver in order to hide identity\nof the former from the latter. The Anonymizer [3] and\nLucent Personalized Web Assistant [22] are examples of\nthis approach. While relatively ef\ufb01cient, it is susceptible\nto a (local) passive adversary that monitors all proxy ac-\n4For\nexample,\na\nname\nsuch\nas:\n/ndn/xerox/parc/Alice/family/photos/Hawaii might\nbe replaced with /ndn/xerox/parc/Alice/encrypted-part.\n3\n\n\ntivity. Also, a centralized proxy necessitates centralized\n(global) trust and represents a single point of failure.\nA more sophisticated decentralized approach is used\nin mix networks [13]. Typically, a mix network achieves\nanonymity by repeatedly routing a message from one\nproxy to another, such that the message gradually loses\nany relationship with its originator. Messages must be\nmade unintelligible to potentially untrusted intermediate\nnodes. Chaum\u2019s initial proposal [13] de\ufb01nes an anony-\nmous email system, wherein a sender envelops a mes-\nsage with several concentric layers of public key encryp-\ntion. The resulting message is then forwarded to a se-\nquence of mix servers, that gradually remove one layer\nof encryption at a time and forward the message to the\nnext mix server.\nSubsequent research generally falls into two classes:\ndelay-tolerant applications (e.g. email, \ufb01le sharing) and\nreal-time or low-latency applications (e.g. web brows-\ning, VoIP, SSH). These two classes achieve different\ntradeoffs between performance (in terms of latency and\nbandwidth) and anonymity. For example, Babel [24],\nMixmaster [30] and Mixminion [16] belong to the \ufb01rst\ncategory. Their goal is to provide anonymity with re-\nspect to the global eavesdropper adversary. Each mix\nintroduces spurious traf\ufb01c and randomized traf\ufb01c delays\nin order to inhibit correlation between input and out-\nput traf\ufb01c. However, unpredictable traf\ufb01c characteris-\ntics and high delays make these techniques unsuitable\nfor many applications.\nLow-latency anonymizing networks are at the other\nend of the spectrum. They try to minimize extra latency\nby forwarding traf\ufb01c as fast as possible. Because of this,\nstrategies used in anonymization of delay-tolerant traf\ufb01c\n\u2013 batching (delaying) and re-ordering of traf\ufb01c in mixes,\nas well as introduction of decoy traf\ufb01c \u2014 are generally\nnot applicable. For example, [40] shows how traf\ufb01c pat-\nterns can be used for de-anonymization in low-latency\nanonymity systems. Notable low-latency tools are sum-\nmarized below.\nCrowds [37] is a low-latency anonymizing network\nfor HTTP traf\ufb01c. It differs from traditional mix-based\napproaches as it lacks layered encryption. For each mes-\nsage it receives, an anonymizer probabilistically chooses\nto either forward it to a random next hop within the\nCrowds network or deliver it to its \ufb01nal destination.\nSince messages are not encrypted, Crowds is vulnerable\nto local eavesdroppers and predecessor attacks [43].\nMorphmix [38, 39] is a fully distributed peer-to-\npeer mix network that uses layered encryption. Unlike\nCrowds, it does not require a lookup service to keep\ntrack of all participating nodes. Senders selects the \ufb01rst\nanonymizer and each anonymizer along an \u201canonymous\ntunnel\u201d picks the next hop to dynamically build tunnels.\nTarzan [21] is another fully distributed peer-to-peer mix\nnetwork. It builds a universally veri\ufb01able set of neigh-\nbors (called mimics) for every node to keep track of\nother other Tarzan participants. Every node selects its\nmimics pseudo-randomly.\nTor [18] is the best-known and most-used low-latency\nanonymizing tool.\nIt is based on onion routing and\nlayered encryption. Tor uses a central directory to lo-\ncate participating nodes and requires users to build a\nthree-hop anonymizing circuit by choosing three ran-\ndom nodes. The \ufb01rst is called the guard, the second\n\u2013 the middle, and the third \u2014 exit node. Once set up,\neach circuit in Tor lasts about 10 minutes. For better\nperformance, bandwidth available to nodes is taken into\naccount during circuit establishment and multiple TCP\nconnections are multiplexed over one circuit. Commu-\nnication between Tor nodes is secured via SSL. How-\never, Tor does not introduce any decoy traf\ufb01c or random-\nization to hide traf\ufb01c patterns. Another anonymization\ntool, I2P [26], adopts many ideas of Tor, while using a\ndistributed untrusted directory service to keep track of\nits participants. I2P also replaces Tor\u2019s circuit-switching\noperation with packet-switching to achieve better load\nbalancing and fault-tolerance.\nA consumer privacy technique for Information-\nCentric Networks (ICNs) is proposed in [4]. Instead of\nusing encryption, it leverages cooperation from content\nproducers and requires them to mix sensitive informa-\ntion with so-called \u201ccover\u201d content. This approach re-\nquires producers to cooperate and store a large amount\nof cover traf\ufb01c.\nIt also does not provide consumer-\nproducer unlinkability or protection against malicious\nproducers.\nTelex [44] is an alternative to mix networks de-\nsigned to evade state-level censorship. It uses stegano-\ngraphic techniques to hide messages in SSL handshakes.\nUsers connect to innocuous-looking unblocked websites\nthrough SSL. Sympathetic ISP-s that forward user\u2019s traf-\n\ufb01c recover hidden messages and deliver them to the in-\ntended destination. While novel, this approach presents\nsigni\ufb01cant deployment challenges and requires support\nfrom the network infrastructure. Furthermore, the threat\nmodel in Telex is quite different from that of the other\nanonymizing tools presented above. Moreover, estab-\nlished TCP \ufb01ngerprinting techniques can easily detect\ndifferences between a Telex station and a censored web-\nsite. Another analogous technique \u2013 called Cirripede\n[25] \u2013 was recently proposed.\n4\nANDaNA\nANDaNA is a onion routing overlay network, built\non top of NDN, that provides privacy and anonymity\nto consumers. In particular, ANDaNA prevents adver-\nsaries from linking consumers with the content they\nare retrieving.\nFollowing the terminology introduced\n4\n\n\nin [37], ANDaNA provides beyond suspicion5 degree of\nanonymity to its users.\nANDaNA uses multiple concentric layers of encryp-\ntion and routes messages from consumers through a\nchain of at least two onion routers. Each router removes\na layer of encryption and forwards the decrypted mes-\nsages to the next hop.\nDue to its low-latency focus,\nANDaNA does not guarantee privacy in presence of a\nglobal eavesdropper. However, since it is geared for a\nworld-wide (or at least geographically distributed) net-\nwork spanning a multitude of administrative domains,\nthe existence of such an adversary is unlikely. For this\nreason, we restrict the adversarial capabilities to eaves-\ndropping on, injecting, removing or modifying mes-\nsages on a subset of available links.\nAn adversary\ncan compromise NDN routers and ANDaNA nodes at\nwill. Nonetheless, consumers bene\ufb01t from anonymity as\nlong as they use at least one non-compromised ANDaNA\nnode. Details of our adversarial model and formal pri-\nvacy guarantees are discussed in Section 5.\n4.1\nDesign\nWe now present two techniques \u2014 asymmetric and\nsession-based \u2014 that provide privacy and anonymity for\nNDN traf\ufb01c. Traf\ufb01c is routed through ephemeral cir-\ncuits, that are de\ufb01ned as a pair of distinct anonymizing\nrouters (ARs). An AR is a NDN node (e.g. a router or a\nhost) that chooses to be part of ANDaNA. An ephemeral\ncircuit transports only one (or only a few) encrypted in-\nterest(s). It disappears either when the corresponding\ncontent gets delivered, or after a short timeout (hence\n\u201cephemeral\u201d). A timeout interval is needed so that the\nconsumer can re-issue the same encrypted interest in\ncase of packet loss. We refer to the \ufb01rst AR as entry\nrouter and the second \u2013 as exit router. They must not\nbelong to the same administrative domain and must not\nshare the same name pre\ufb01x. Optionally, consumers can\nselect ARs according to some parameters, such as adver-\ntised bandwidth, availability or average load. As pointed\nout in [5, 31], there is a well know natural tension be-\ntween non-uniform (i.e. performance-driven) choice of\nrouters and anonymity. Consumers should consider this\nwhen selecting ARs.\nTo build an ephemeral circuit, a consumer retrieves\nthe list of ARs and corresponding public keys. Although\nwe do not mandate any particular technique, a consumer\ncan retrieve this list using, e.g., a directory service [18]\nor a decentralized (peer-to-peer) mechanism. AR pub-\nlic keys can be authenticated using decentralized tech-\nniques (such as web-of-trust [2]) or a PKI infrastruc-\nture.6\n5For any packet observed by the adversary, an entity is considered\nbeyond suspicion if it is as likely to be the sender of this packet as any\nother entity.\n6Note that implicit replication implemented through caching al-\nA prospective AR joins ANDaNA by advertising its\npublic key, together with its identity de\ufb01ned as: names-\npace, organization and public key \ufb01ngerprint. An AR\nalso publishes auxiliary information, such as total band-\nwidth, average load, and uptime.\nAs mentioned earlier, both interest and content pack-\nets leak information. Even if names in interests are hid-\nden, three components of content packets \u2014 signatures,\nnames and content itself \u2014 contain potentially sensitive\ninformation. Of course, content producers could sim-\nply generate a new key-pair to sign each content packet.\nThis would be impractical, since high costs of key gen-\neration and distribution would make it dif\ufb01cult for con-\nsumers to authenticate content. (Note that key-evolving\nschemes [8] do not help, since veri\ufb01cation keys gener-\nally evolve in a way that is predictable to all parties, in-\ncluding the adversary.) Alternatively, the original con-\ntent signature could be replaced with that generated by\nan AR. However, this would preclude end-to-end con-\ntent veri\ufb01ability and thus break the NDN trust model.\nFor this reason, ANDaNA implements encrypted en-\ncapsulation of original content, using two symmetric\nkeys securely distributed by the consumer to the ARs\nduring setup of the ephemeral circuit. Upon receiving a\ncontent packet, the exit router encrypts it, together with\nthe original (cleartext) name and signature, under the\n\ufb01rst key provided by the consumer. Then, treating the\nciphertext as payload for a new content packet, the exit\nrouter signs and sends it to the entry router. The latter\nstrips this signature and the name and encrypts the re-\nmaining ciphertext under the second symmetric key pro-\nvided by the consumer. Next, it forwards the ciphertext\nwith the original encrypted name and a fresh (its own)\nsignature. After decrypting the payload, the consumer\ndiscards the signature from the entry router and veri\ufb01es\nthe one from the content producer.\nBecause decryption is deterministic, an encrypted in-\nterest sent to an AR always produces the same output.\nSince ARs are a public resource, the adversary can use\nthem to decrypt previously observed interests. It can\nthus observe the corresponding output and correlate in-\ncoming/outgoing interests. This is a well-known attack\nand there are several ways to mitigate it, such as en-\ncrypted channels between communicating parties [18]\nand mixing (for delay-tolerant traf\ufb01c) [24]. However,\nsuch techniques tend to have signi\ufb01cant impact on com-\nputational costs and latency. Instead, we use standard\nNDN features of interest aggregation and caching to pre-\nvent such attacks, as described next.\nIn NDN, a router (not just an AR) that receives dupli-\ncate interests collapses them. An interest is considered\na duplicate, if it arrives while another interest referring\nlows the construction of a directory system with better resilience\nagainst denial-of-service (DoS) attacks than IP.\n5\n\n\nto the same content has not been satis\ufb01ed. Also, if the\noriginal interest has been satis\ufb01ed and the correspond-\ning content is still in cache, a new interest requesting\nthe same piece of data is satis\ufb01ed with cached content.\nIn this case, the router does not forward any interests.\nTherefore, the adversary must wait for the expiration of\ncached content.\nAs part of ANDaNA, the consumer includes its current\ntimestamp within each encryption layer. ARs reject in-\nterests with timestamps outside a pre-de\ufb01ned time win-\ndow. Thus, consumers need to be loosely synchronized\nwith ARs that must reserve at least (rate \u00d7 window) of\ncache, where rate is the router\u2019s wire-rate and window\nis the interval within which interests are accepted. In\nthis way, if an interest is received multiple times by an\nAR (e.g. in case of loss of the corresponding data packet\nbetween the AR and the consumer), the AR is able to\nsatisfy it using its cache.\nThe encryption algorithm used by consumers to con-\nceal names in interests must be secure against adap-\ntive chosen ciphertext (CCA) attacks.7\nCCA-security\n[9] implies, among other things, probabilistic encryption\nand non-malleability. The former prevents the adversary\nfrom determining whether two encrypted interests cor-\nrespond to the same unencrypted interest. Whereas, the\nlatter implies that the adversary cannot modify interests\nto defeat the mechanism described above.\nWe now describe two \ufb02avors of anonymization pro-\ntocols: asymmetric and session-based. In order to al-\nlow ef\ufb01cient routing of interest packets, the encrypted\ncomponent is encoded at the end of the name with both\n\ufb02avors.\nAsymmetric: To issue an interest, a consumer selects\na pair of ARs and uses their public keys to encrypt the\ninterest, as described above and in Algorithm 1. A con-\nsumer also generates two symmetric keys: k1 and k2\nthat will be used to encrypt the content packet on the\nway back. We use Epk(\u00b7) and Ek(\u00b7) to denote (CCA-\nsecure) public key and symmetric encryption schemes,\nrespectively.\nTo account for the delay due to extra hops needed\nto reach the second AR (and reduce the number of dis-\ncarded interests), a consumer adds half of the estimated\nround trip time (RTT) to the innermost timestamp. Each\nAR removes the outermost encryption layer, as detailed\nin Algorithm 2. Since Epk(\u00b7) is CCA-secure, the decryp-\ntion process fails if the ciphertext has been modi\ufb01ed in\ntransit or was not encrypted under the AR\u2019s public key.\nContent corresponding to the encrypted interest is en-\ncrypted on the way back, as detailed in Algorithm 3, us-\n7Technically, in order to guarantee correctness an encryption\nscheme suitable for ANDaNA must also be robust [1]. However, since\nCCA-secure encryption schemes used in practice are also robust, we\nomit this requirement in the rest of the paper.\nAlgorithm 1: Encrypted Interest Generation\ninput : Interest int; Set of \u2113ARs and their keys:\nR = {(ARi, pki) | 0 < i \u2264\u2113, pki \u2208PK}\noutput: Encrypted interest intpki,pkj ; symmetric keys k1, k2\n1: Select (ARi, pki), (ARj, pkj) from R\n2: if ARi = ARj or ARi, ARj are from same organization or\nARi, ARj share the same name pre\ufb01x then\n3:\nGo to line 1\n4: end if\n5: k1 \u2190{0, 1}\u03ba ; k2 \u2190{0, 1}\u03ba\n6: eint = AR2/Epkj (int | k2 | curr timestamp + RTT/2)\n7: eint = AR1/Epki(eint | k1 | curr timestamp)\n8: Output eint, k1, k2\nAlgorithm 2: AR Handling of Encrypted Interests\ninput : Encrypted Interest intpki,pkj , where\npki, pkj \u2208PK \u222a{\u22a5}\n(where \u201c\u22a5\u201d denotes \u201cno\nencryption\u201d)\noutput: Interest intpkj ; symmetric key k1\n1: (intpkj , k1, timestamp) = Dski(intpki,pkj )\n2: if Step 1 fails or timestamp is not current then\n3:\nDiscard intpki,pkj\n4: else\n5:\nSave tuple (intpki,pkj , intpkj , k1) to internal state\n6:\nOutput intpkj , k1\n7: end if\nAlgorithm 3: AR Content Routing\ninput : Content: datak2 in response to intpkj , where\npkj \u2208PK \u222a{\u22a5}\noutput: Encrypted data packet datak1,k2\n1: Retrieve tuple (intpki,pkj , intpkj , k1) from internal state\nwhere name in intpk2 matches that in datak2\n2: if k2 \u0338= \u22a5then Remove signature and name from datak2\n3: Create new empty data packet pkt\n4: Set name on pkt as the name on intpki,pkj\n5: Set the data in pkt as Ek1(datak2 )\n6: Sign pkt with AR\u2019s key\n7: Output pkt as datak1,k2\ning Ek(\u00b7) and symmetric keys supplied by the consumer.\nSession-based Variant.\nThis variant aims to reduce\n(amortize) the use of public key encryption thus lower-\ning the computational cost and ciphertext size. Before\nsending any interests through ephemeral circuits, a con-\nsumer (Alice) establishes a shared secret key with each\nselected AR. This is done via a 2-packet interest/content\nhandshake. We do not describe the details of symmet-\nric key setup, since there are standard ways of doing\nit. We provide two options: one using Dif\ufb01e-Hellman\nkey exchange [17], and the other \u2013 using SSL/TLS-style\nprotocol whereby Alice encrypts a key for ARi. Once a\nsymmetric key kai is shared with ARi, Alice can estab-\nlish any number of ephemeral circuits using it as either\n\ufb01rst or second AR hop. Also at setup time, Alice and\nARi agree on session identi\ufb01er value \u2013 sidai \u2013 that is in-\ncluded (in cleartext) in subsequent interests so that ARi\n6\n\n\ncan identify the appropriate entry for Alice and kai.\nThe main advantage of the session-based approach\nis better performance: both consumers and routers only\nperform symmetric operations after initial key setup.\nHowever, one drawback is that, since the session iden-\nti\ufb01er sid is not encrypted, packets corresponding to the\nsame sid are easily linkable.\nWe note that our design neither encourages nor pre-\nvents consumers from mixing asymmetric and session-\nbased variants for the same or different ephemeral cir-\ncuits.\n4.2\nSystem and Security Model\nIn order for our discussion to relate to prior work,\nwe use the notion of \u201cindistinguishable con\ufb01gurations\u201d\nfrom the framework introduced in [19]; the actual de\ufb01-\nnitions are in Section 5.\nOur security analysis considers the worst case sce-\nnario, i.e., interests being satis\ufb01ed by the content pro-\nducer rather than a router\u2019s cache. While, in normal\nconditions, encrypted interests are satis\ufb01ed by caches\nonly in case of packet loss, fully decrypted interests may\nnot have to reach to content producers. A system se-\ncure in case of cache misses is also secure when interests\nare satis\ufb01ed by content cached at routers along the way.\n(Recall that, when an interest is satis\ufb01ed by a router\u2019s\ncache, it is not forwarded any further.) This limits the\nadversary\u2019s ability to observe interests in transit.\nAdversary Goals and Capabilities.\nThe goal of an\nadversary is to link consumers with their actions. In par-\nticular, it may want to determine what content is being\nrequested by a particular user and/or which users are re-\nquesting speci\ufb01c content. A somewhat related goal is\ndetermining which cache (if any) is satisfying a con-\nsumer\u2019s requests. Our adversary is local and active: it\ncontrols only a subset of network entities and can per-\nform any action usually allowed to such entities. More-\nover, it is capable of selectively compromising addi-\ntional network entities according to its local information.\nOur model allows the adversary to perform the fol-\nlowing actions:\n\u2022 Deploy compromised routers:\nANDaNA is an\nopen network, therefore an adversary can deploy\ncompromised anonymizers and regular routers. As\nsuch, routers may exhibit malicious behavior in-\ncluding injection, delay, alteration, or drop traf\ufb01c.\n\u2022 Compromise existing routers: An adversary can\nselect any router (either ARs or regular routers) in\nthe network and compromise it. As a result, the ad-\nversary learns all the private information (e.g. de-\ncryption keys, pending decrypted interests, cache\ncontent, etc.) of such router.\n\u2022 Control content producers: Content producers\nare not part of ANDaNA. As such, the network has\nno control over them. An adversary can compro-\nmise existing content producers or deploy compro-\nmised ones and convince users to pull content from\nthem. We also assume that the content providers\nare publicly accessible, and therefore the adversary\nis able to retrieve content from them.\n\u2022 Deploy compromised caches: Similarly to com-\npromised content producers, an adversary can com-\npromise routers\u2019 cache or deploy its own caches.\nThe behavior of a compromised cache includes\nmonitoring cache requests and replying with cor-\nrupted data.\n\u2022 Observe and replay traf\ufb01c: An adversary can tap\na link carrying anonymized traf\ufb01c. By doing this\nit learns, among other things, packet contents and\ntraf\ufb01c patterns. The traf\ufb01c observed by an adver-\nsary can be replayed by any compromised router.\nAn adversary can iteratively compromise entities of its\nchoice, and use the information it gathers to determine\nwhat should be compromised next. In order to make\nour model realistic, the time required by an adversary\nto compromise or deploy a router, a cache or a con-\ntent producer is signi\ufb01cantly higher that the round-trip\ntime (RTT) of an anonymized interest and correspond-\ning data. This implies that all the state information re-\ncovered from a newly compromised router only refers to\npackets received after the adversary decides to compro-\nmise such router.\nA powerful class of attacks against anonymizing net-\nworks is called \ufb01ngerprinting [29, 41].\nInter-packet\ntime intervals are usually not hidden in low latency\nonion routing networks because packets are dispatched\nas quickly as possible. This behavior can be exploited\nby an adversary, who can correlate inter-packet intervals\non two links and use this information to determine if\nthe observed packets belong to the same consumer [41].\nThis class of attacks is signi\ufb01cantly harder to execute on\nANDaNA because of the nature of ephemeral circuits and\nbecause of the use of caches on routers. Ephemeral cir-\ncuits do not allow the adversary to gather enough pack-\nets with uniform delays since they are used to transport\nonly one or a very small number of interests and corre-\nsponding data. Active adversaries who can control the\ncommunication link of a content provider can add mea-\nsurable delays to some of the packets in order to identify\nconsumers. However, consumers may be able to retrieve\nthe same content through caches making such attack in-\neffective. Throughput \ufb01ngerprinting consists in measur-\ning the throughput of the circuit used by a consumer to\nidentify the slowest anonymizer in the consumer\u2019s cir-\ncuit [29]. Throughput \ufb01ngerprinting is dif\ufb01cult to per-\nform in ANDaNA since each ephemeral circuit does not\ncarry enough information to mount an attack. In par-\nticular, the authors of [29] report that a successful at-\n7\n\n\ntack requires at least a few minutes of traf\ufb01c on Tor.\nSimilarly, ephemeral circuits provide an effective pro-\ntection against known attacks such as the predecessor\nattack [43].\nConsumers, Producers and ARs. Each consumer runs\nseveral processes that generate interests. For our analy-\nsis, interests are created by a speci\ufb01c interface of a host,\nand the corresponding content is delivered back to the\nsame interface. Interest encryption is either performed\non the consumer\u2019s host, or on an entity that routes con-\nsumer\u2019s traf\ufb01c. In the latter case, the channel between\nthe user and the anonymizing entity is considered se-\ncure.\nContent is generated by producers, i.e., entities that\ncan sign data. We do not assume the correspondence\nbetween a producer and a particular host. Content can\nbe either stored in routers\u2019 caches, at servers or dynami-\ncally generated in response to an interest.\nARs perform interests decryption and content encap-\nsulation. Each AR advertises a public key for signature\nveri\ufb01cation and one or more public keys for encryption.\nARs must refresh their encryption keys frequently, dis-\ncarding old keys after a short grace period. In order to\nsimplify key distribution and allow consumer to imme-\ndiately trust new public keys from routers, we use a sim-\nple key hierarchy where a long lived public key owned\nby the router (the signing key), is used to certify short\nlived encryption keys. The signing key may be certi\ufb01ed\nby other entities using techniques like web-of-trust or\nPKI.\nDenial-of-service Attacks. ANDaNA is envisioned as a\npublic overlay network and is clearly susceptible to DoS\nattacks. Since anyone can join ANDaNA as an AR or\nuse it as a consumer, we make no distinction between\ninsider and outsider attacks. The adversary can send nu-\nmerous interests to ARs or construct ephemeral circuits\nlonger than two hops in order to maximize effective-\nness of attacks. Moreover, it can consume AR resources\nby sending malformed encrypted interests that require\nARs to perform expensive and ultimately useless public\nkey decryption. Similar to Tor, before establishing an\nephemeral circuit, an AR can ask a consumer to solve an\neasy-to-verify/expensive-to-solve puzzle. This and sim-\nilar techniques for ANDaNA are subjects of future work.\nIn a setting with long-lived circuits, such as Tor, disrupt-\ning a node effectively shuts down all circuits that include\nit. Due to the short lifespan of our ephemeral circuits,\nthe same attack on ANDaNA only causes a very small\nnumber of interests/data packets per user to be dropped.\nAbuse.\nSimilar to any other anonymity service,\nANDaNA can be abused for a variety of nefarious pur-\nposes. We do not elaborate on this topic. However, exit\npolicies similar to those in Tor [18] can be used with\nANDaNA based on content names.\n5\nSecurity Analysis\nIn this section we propose a formal model for eval-\nuating the security of ANDaNA. We de\ufb01ne consumer\nanonymity and unlinkability with respect to an adver-\nsary within this model. We \ufb01nally provide necessary\nand suf\ufb01cient conditions for anonymity and unlinkabil-\nity. As our analysis shows, we are able to obtain a level\nof anonymity comparable to Tor with two \u2014 rather than\nTor\u2019s three \u2014 ARs thanks to the lack of source addresses\nin NDN interests.\nIn general, ef\ufb01cacy of ANDaNA depends on the in-\nability of the adversary to correlate input and output\nof a non-compromised AR, and its inability to observe\nall producer and consumers at the same time.\nSince\nANDaNA is designed for low-latency traf\ufb01c, we do not\nintentionally delay messages or introduce dummy pack-\nets, other than some limited padding. This is similar to\nhow Tor and other low-latency anonymizing networks\nforward traf\ufb01c, and implies that traf\ufb01c patterns remain\nalmost unchanged as they pass through the network [31].\nIt is well known that, in Tor, this allows the adversary\nthat observes both ends of a communication \ufb02ow to con-\n\ufb01rm a suspected link between them [5, 35]. For this rea-\nson, a global passive adversary can violate anonymity\nproperties of both Tor and ANDaNA. However, we be-\nlieve that such an adversary is unrealistic in a geographi-\ncally distributed network spanning over multiple admin-\nistrative domains, and designing against it would result\nin overkill.\nWe assume that any adversary monitoring all inter-\nfaces of an AR can correlate entering encrypted traf\ufb01c\nwith its exiting, decrypted counterpart using timing in-\nformation. However, we believe that the short lifespan\nof ephemeral circuits \u2013 and therefore the limited num-\nber of related packets traveling through a single AR \u2013\nseverely limits the adversary\u2019s ability to carry out this\nattack.\nUnfortunately, at the time of this writing we\ndo not have enough experimental evidence to con\ufb01rm\nthis. For the sake of safety, in the analysis below we\nassume that, by compromising all interfaces of an AR,\nthe adversary also compromises the AR itself. There-\nfore, a non-compromisedAR must have at least one non-\ncompromised interface. To sum up, we assume that:\nAssumption 5.1. Adv cannot correlate input and out-\nput of a non-compromised AR.\nOur analysis is based on indistinguishable con\ufb01gura-\ntions. A con\ufb01guration de\ufb01nes consumers\u2019 activity with\nrespect to a particular network. Adv only controls a sub-\nset of network entities and observes only some pack-\nets. Therefore, it cannot distinguish between two con-\n\ufb01gurations that vary only in the activity that it cannot\ndirectly observe or in the content of encrypted pack-\nets that it cannot decrypt. In order to provide mean-\n8\n\n\ningful anonymity guarantees, we identify a set of con-\n\ufb01gurations that have one or more equivalent counter-\nparts. However, unlike [19], our analysis takes into ac-\ncount the infrastructure underlying ANDaNA, i.e., the\nnetwork topology and packets exchanged over the ac-\ntual network. We believe that this makes our model and\nanalysis both realistic and \ufb01ne-grained, since it accounts\nfor all adversarial advantages related to the underlying\nnetwork structure. Packets sent by a non-compromised\nconsumer u to a non-compromised AR r transit through\nseveral \u2014 possibly compromised \u2014 NDN routers that\nare not part of ANDaNA. The model of [19] considers r\ncompromised even if only one link between u and r is\ncontrolled by the adversary. Whereas, in our model, r is\nconsidered to be non-compromised.\nNotation and De\ufb01nitions\nTable 1 summarizes our notation. The intersection of\nP and C might not be empty, which re\ufb02ects the fact that\nconsumers can act as producers and vice versa. Sim-\nilarly, our model does not prevent routers from being\nproducers and/or consumers. Therefore, R\u2229P and R\u2229C\nmight be non-empty.\nThe adversary is de\ufb01ned as a 4-tuple:\nAdv\n=\n(PAdv, CAdv, RAdv, IFAdv) \u2282(P, C, R, IF) where indi-\nvidual components specify (respectively) sets of: com-\npromised producers, consumers, routers and interfaces.\nIf r \u2208RAdv, then Adv controls all interfaces and has ac-\ncess to all decryption key and state information of r. If\nall interfaces of r are in IFAdv, then r \u2208RAdv. In other\nwords, for the sake of this analysis, controlling all in-\nterfaces of a router is equivalent to learning that router\u2019s\ndecryption/secret key. We emphasize that for r \u2208R to\nbe non-compromised, at least one of its interfaces must\nbe non-compromised. If p \u2208PAdv, Adv controls p\u2019s\ninterfaces, monitors interests received by p and controls\nboth content and timing of p\u2019s responses to incoming in-\nterests. If c \u2208CAdv, then Adv controls all \ufb01elds and\ntiming of interests. Finally, if if \u2208IFAdv, then Adv can\nlisten to all traf\ufb01c \ufb02owing through if, as well as send-\ning new traf\ufb01c from it. IFAdv includes all the interfaces\nof compromised consumers, producers and routers plus\nadditional interfaces eavesdropped on by Adv.\nFor ease of notation, we do not explicitly indicate the\nname of the next router in interest packets nor symmetric\nkeys chosen by consumers. We denote encrypted inter-\nests as:\nintpk1,pk2 = Epk1(Epk2(int))\nwith pk1, pk2 \u2208PK \u222a{\u22a5} where \u22a5indicates a special\nsymbol for \u201cno encryption\u201d. If pk1 = \u22a5then pk2 = \u22a5.\nThe size of public keys is a function of the global se-\ncurity parameter \u03ba. For simplicity, we denote intpk1,\u22a5\nas intpk1. When an AR receives intpk1,pk2 and if it is in\npossession of the decryption key corresponding to pk1, it\nremoves the outer layer of encryption. While E is CCA-\nsecure (and therefore also CPA-secure), we do not re-\nquire E to be key private [6]. Key privacy prevents an\nobserver from learning the public key used to generate\na ciphertext. In ANDaNA, knowledge of the public key\nused to encrypt the outer layer of an interest does not re-\nveal any more information than the (cleartext) name on\nthe interest.\nWe de\ufb01ne the anonymity set with respect to interface\nifr\ni as:\nAifr\ni = {d | Pr [d \u2192int r | int \u2740ifr\ni ] > 0}\nIn other words, for each interface ifr\ni of router r, Aifr\ni\ncontains all entities that could have sent int with non-\nzero probability. We de\ufb01ne pathint = {ifr\ni | int \u2740ifr\ni }.\nThis is the sequence of interfaces traversed by int. We\nuse it to de\ufb01ne the anonymity set of an interest with re-\nspect Adv:\nAint\nAdv \u225c\n\\\npathint\u2229IFAdv\nAifr\ni\nIntuitively, if u is far away from a compromised entity\nd, then all sets Aint\nAdv such that u \u2208Aint\nAdv are a large\nsubset of C. Adv can rule out possible senders of an in-\nterest (i.e., determine if u /\u2208Aint\nAdv) only if it controls\nat least one entity (routers, interfaces) along each path\nthat u does not share with other consumers. The level of\nanonymity of u \u2208Aint\nAdv with respect to Adv is propor-\ntional to the size of Aint\nAdv. In particular, if u is the only\nmember of Aint\nAdv, it has no anonymity, since int must\nhave been issued by u.\nA con\ufb01guration is a description of the network activ-\nity. Each con\ufb01guration maps consumers to their actions,\nde\ufb01ned as the interest they issue and the corresponding\ncontent producers. More formally, a con\ufb01guration is a\nrelation:\nC : C \u2192{(r1, r2, p, intpk1,pk2)}\nwith (r1, r2, p, intpk1,pk2) \u2208R2\u00d7P\u00d7{0, 1}\u2217, that maps\na consumer to: a pair of routers de\ufb01ning an ephemeral\ncircuit, an interest (encrypted for this circuit) and a pro-\nducer. C(u) is a 4-tuple that represents one action of u\nin C. Ci is the selection on the i-th component of C,\ni.e., if C(u) = (r1, r2, p, intpk1,pk2), then C1(u) = r1,\nC2(u) = r2, C3(u) = p and C4(u) = intpk1,pk2.\nWe say that two con\ufb01gurations C and C\u2032 are \u201cindis-\ntinguishable with respect to Adv\u201d if Adv can only de-\ntermine with probability at most 1/2 + \u03b5 which con\ufb01g-\nuration corresponds to the observed network, for some\n\u03b5 negligible in the security parameter \u03ba. We denote two\nsuch con\ufb01gurations as C \u2261Adv C\u2032.\nWe now show that assumption 5.1 holds if a pas-\nsive adversary observes only input and output values of\n9\n\n\nC\nset of all consumers, u \u2208C\nAdv\nadversary\nP\nset of all content producers, p \u2208P\nd\nan entity, i.e., a router or a host\nR\nset of all routers, r \u2208R\nd \u2192int r\nentity d sends interest int to some interface of router r\nIF\nset of all interfaces on all network devices\nint \u2740ifr\ni\nrouter r receives interest int on interface ifr\ni\nifr\ni \u2208IF\ni-th interface on router r\nEpk(\u00b7)\nCCA-secure hybrid encryption scheme\nPK\nset of all public keys\nintpk1,pk2\ninterest encrypted under public keys pk1, pk2\n(pki, ski)\npublic/priv. encryption keypair of an AR ri\n\u22a5\nno encryption\nTable 1. Notation.\nan AR (i.e., it cannot use timing information or other\nside-channels), and the underlying encryption scheme\nis semantically secure. Claim 5.1 below states that, for\nany encrypted interest, Adv cannot determine if it corre-\nsponds to an interest decrypted by a non-compromised\nrouter, by observing the two and with no additional in-\nformation.\nClaim 5.1. Given any CPA-secure public key encryp-\ntion scheme E and two same-length interests int0, int1\nchosen by Adv, Adv has only negligible advantage over\n1/2 in determining the value of a randomly selected bit\nb, given intb\npk1,pk2, int0\npk2 and int1\npk2, with pk1 \u2208PK\nand pk2 \u2208PK \u222a{\u22a5}.\nDue to the lack of space, Claim 5.1 is formally justi\ufb01ed\nin Appendix A.\nAnonymity De\ufb01nitions and Conditions\nIn this section we present formal de\ufb01nitions of\nanonymity for our model. We introduce the notions of\nconsumer anonymity, producer anonymity and producer\nand consumer unlinkability. We show that ephemeral\ncircuits composed of two anonymizing routers \u2014 at\nleast one of which is not compromised \u2014 provide con-\nsumer and producer anonymity. This, in turn, implies\nconsumer and producer unlinkability. Due to the lack\nof space, we defer forma",
  "downloaded_at": "2026-04-23 22:42:13"
}